osm_api/__init__.py
osm_api/api.py
osm_api/core.py
osm_api/parser.py
osmapi_wrapper-1.0.2.dist-info/LICENSE
osmapi_wrapper-1.0.2.dist-info/METADATA
osmapi_wrapper-1.0.2.dist-info/WHEEL
osmapi_wrapper-1.0.2.dist-info/top_level.txt
osmapi_wrapper-1.0.2.dist-info/RECORD
