Metadata-Version: 2.1
Name: osmapi-wrapper
Version: 1.0.2
Summary: A small package to get data from OSM API directly
Author-email: Mohammad Hossein Zendehpey <m.h.Zendehpey@gmail.com>
Project-URL: Homepage, https://github.com/mhzendehpey/osm-api
Project-URL: Bug Tracker, https://github.com/mhzendehpey/osm-api/issues
Classifier: Programming Language :: Python :: 3
Classifier: License :: OSI Approved :: MIT License
Classifier: Operating System :: OS Independent
Requires-Python: >=3.7
License-File: LICENSE
Requires-Dist: requests (>=2.27.1)
Requires-Dist: shapely (>=1.8.2)
